materialxusd/__init__.py
materialxusd/__main__.py
materialxusd/materialxusd.py
materialxusd/materialxusd_custom.py
materialxusd/materialxusd_utils.py
materialxusd/mtlx2usd.py
materialxusd/preprocess_mtlx.py
materialxusd/usd_mtlx_ref.py
materialxusd/data/camera.usd
materialxusd/data/camera.usda
materialxusd/data/camera_sphere.usda
materialxusd/data/environment.usda
materialxusd/data/san_giuseppe_bridge.hdr
materialxusd/data/shaderball.usd
materialxusd/data/shaderball.usda
materialxusd/data/sphere.usd
materialxusd/data/sphere.usda
materialxusd-0.25.5.dist-info/LICENSE
materialxusd-0.25.5.dist-info/METADATA
materialxusd-0.25.5.dist-info/WHEEL
materialxusd-0.25.5.dist-info/entry_points.txt
materialxusd-0.25.5.dist-info/top_level.txt
materialxusd-0.25.5.dist-info/RECORD
