Metadata-Version: 2.1
Name: materialxusd
Version: 0.25.5
Summary: Utilities for MaterialX and USD
Author-email: Bernard Kwok <kwokcb@gmail.com>
License: Apache License
Classifier: Intended Audience :: Developers
Classifier: Programming Language :: Python :: 3
Classifier: License :: OSI Approved :: Apache Software License
Classifier: Operating System :: OS Independent
Classifier: Topic :: Software Development :: Libraries :: Python Modules
Requires-Python: >=3.8
License-File: LICENSE
Requires-Dist: materialx==1.39.3
